tfex/__init__.py
tfex/tfex.py
tfex-0.0.6.dist-info/LICENSE
tfex-0.0.6.dist-info/METADATA
tfex-0.0.6.dist-info/WHEEL
tfex-0.0.6.dist-info/top_level.txt
tfex-0.0.6.dist-info/RECORD
